stecosystems/__init__.py
stecosystems/base.py
stecosystems/deprecated.py
stecosystems/npm.py
stecosystems/pypi.py
strudel.ecosystems-0.0.2.dist-info/LICENSE.txt
strudel.ecosystems-0.0.2.dist-info/METADATA
strudel.ecosystems-0.0.2.dist-info/RECORD
strudel.ecosystems-0.0.2.dist-info/WHEEL
strudel.ecosystems-0.0.2.dist-info/top_level.txt
