Metadata-Version: 2.1
Name: strudel.ecosystems
Version: 0.0.2
Summary: Ecosystem abstractions for PyPI and npm
Home-page: https://github.com/cmustrudel/strudel.ecosystems
Author: Marat (@cmu.edu)
License: GPL v3
Platform: Linux
Platform: Solaris
Platform: Mac OS-X
Platform: Unix
Platform: Windows
Classifier: Development Status :: 4 - Beta
Classifier: Intended Audience :: Science/Research
Classifier: Programming Language :: Python :: 2.7
Classifier: Programming Language :: Python :: 3.4
Classifier: Programming Language :: Python :: 3.5
Classifier: Programming Language :: Python :: 3.6
Classifier: Programming Language :: Python :: 3.7
Classifier: License :: OSI Approved :: GNU General Public License v3 (GPLv3)
Classifier: Operating System :: POSIX :: Linux
Classifier: Topic :: Scientific/Engineering
Requires-Python: >2.6, !=3.0.*, !=3.1.*, !=3.2.*, !=3.3.*, <4
Requires-Dist: ijson
Requires-Dist: pandas
Requires-Dist: requests
Requires-Dist: six
Requires-Dist: strudel.utils
Requires-Dist: strudel.scraper
